<?xml version="1.0" encoding="iso-8859-1" ?>
<newsitem itemid="247537" id="root" date="1996-12-10" xml:lang="en">
<title>USA: Dow seen higher at open, chip stocks seen firm.</title>
<headline>Dow seen higher at open, chip stocks seen firm.</headline>
<dateline>NEW YORK 1996-12-10</dateline>
<text>
<p>Wall Street stocks are expected to open higher on Tuesday, boosted by new evidence of improving conditions in the semiconductor industry, share analysts said.</p>
<p>The Semiconductor Industry Association reported late Monday that its book-to-bill ratio, which measures new orders against shipments, rose to 1.15 in November, a better than expected improvement from October's revised 1.11 reading.</p>
<p>&quot;Chip stocks are higher in Europe and that should help the market get off to a good start,&quot; said Larry Wachtel, market analyst at Prudential Securities.</p>
</text>
<copyright>(c) Reuters Limited 1996</copyright>
<metadata>
<codes class="bip:countries:1.0">
  <code code="USA">
    <editdetail attribution="Reuters BIP Coding Group" action="confirmed" date="1996-12-10"/>
  </code>
</codes>
<dc element="dc.date.created" value="1996-12-10"/>
<dc element="dc.publisher" value="Reuters Holdings Plc"/>
<dc element="dc.date.published" value="1996-12-10"/>
<dc element="dc.source" value="Reuters"/>
<dc element="dc.creator.location" value="NEW YORK"/>
<dc element="dc.creator.location.country.name" value="USA"/>
<dc element="dc.source" value="Reuters"/>
</metadata>
</newsitem>
