<?xml version="1.0" encoding="iso-8859-1" ?>
<newsitem itemid="335731" id="root" date="1997-01-27" xml:lang="en">
<title>USA: Plano, Texas, GOs priced to yield 5.65 pct in 2017.</title>
<headline>Plano, Texas, GOs priced to yield 5.65 pct in 2017.</headline>
<text>
<p>PRELIMINARY PRICING:</p>
<p>CITY OF PLANO, TEXAS</p>
<p>COLLIN AND DENTON COUNTIES</p>
<p>RE: $25,845,000*</p>
<p>GENERAL OBLIGATION BONDS</p>
<p>SERIES 1997</p>
<p>PLEASE INCLUDE ZIP-CODES WITH LOCAL RETAIL ORDERS.</p>
<p>										MOODY'S: Aa</p>
<p>	 S&amp;P: AA</p>
<p>DATED: 01/15/1997</p>
<p>FIRST COUPON: 09/01/1997</p>
<p>DUE: 09/01</p>
<p> MATURITY		AMOUNT*    COUPON	   PRICE</p>
<p>09/01/1998		  795M    6.75  %	  3.90</p>
<p>						 (Approx. $ Price 104.142)</p>
<p>09/01/1999		  825M    6.75  %	  4.15</p>
<p>						 (Approx. $ Price 106.139)</p>
<p>09/01/2000		  860M    6.75  %	  4.35</p>
<p>						 (Approx. $ Price 107.736)</p>
<p>09/01/2001		  895M    5.625 %	  4.45</p>
<p>						 (Approx. $ Price 104.754)</p>
<p>09/01/2002		  940M    4.55  %	  4.55</p>
<p>09/01/2003		  980M    4.65  %	100.00</p>
<p>09/01/2004		1,030M    4.75  %	100.00</p>
<p>09/01/2005		1,080M    4.85  %	100.00</p>
<p>09/01/2006		1,135M    4.95  %	100.00</p>
<p>09/01/2007		1,190M    5.05  %	100.00</p>
<p>09/01/2008		1,250M    5.15  %	100.00</p>
<p>09/01/2009		1,315M    5.25  %	100.00</p>
<p>09/01/2010		1,390M    5.35  %	100.00</p>
<p>09/01/2011		1,465M    5.45  %	100.00</p>
<p>09/01/2012		1,545M    5.50  %	100.00</p>
<p>09/01/2013		1,630M    5.55  %	100.00</p>
<p>09/01/2017		7,520M    5.60  %	  5.65</p>
<p>						 (Approx. $ Price 99.396)</p>
<p>CALL FEATURES: 09/01/2007    100.00</p>
<p>* - APPROXIMATE SUBJECT TO CHANGE</p>
<p>The award is expected Monday, January 27, 1997.</p>
<p>Delivery is expected on February 27, 1997.</p>
<p>Smith Barney Inc.</p>
<p>Compass Bank</p>
<p>Pryor, McClendon, Counts &amp; Co., Inc.</p>
<p>--U.S. Municipal Desk, 212-859-1650</p>
</text>
<copyright>(c) Reuters Limited 1997</copyright>
<metadata>
<codes class="bip:countries:1.0">
  <code code="USA">
    <editdetail attribution="Reuters BIP Coding Group" action="confirmed" date="1997-01-27"/>
  </code>
</codes>
<codes class="bip:topics:1.0">
  <code code="E21">
    <editdetail attribution="Reuters BIP Coding Group" action="confirmed" date="1997-01-27"/>
  </code>
  <code code="E212">
    <editdetail attribution="Reuters BIP Coding Group" action="confirmed" date="1997-01-27"/>
  </code>
  <code code="ECAT">
    <editdetail attribution="Reuters BIP Coding Group" action="confirmed" date="1997-01-27"/>
  </code>
</codes>
<dc element="dc.publisher" value="Reuters Holdings Plc"/>
<dc element="dc.date.published" value="1997-01-27"/>
<dc element="dc.source" value="Reuters"/>
<dc element="dc.creator.location.country.name" value="USA"/>
<dc element="dc.source" value="Reuters"/>
</metadata>
</newsitem>
