<?xml version="1.0" encoding="iso-8859-1" ?>
<newsitem itemid="590578" id="root" date="1997-05-16" xml:lang="en">
<title>FRANCE: EU grain export commitments reach 26.56 mln tns.</title>
<headline>EU grain export commitments reach 26.56 mln tns.</headline>
<dateline>PARIS 1997-05-16</dateline>
<text>
<p>European Union grain export commitments up to May 13 rose 62.4 percent over last year, official figures showed on Friday.</p>
<p>Figures supplied by member country officials showed grain earmarked for export between July 1, 1996 and May 13, 1997 totalled 26.56 million tonnes against 16.356 million during the same period last year.</p>
<p>Exports of commercial soft wheat grain reached 9.786 million tonnes against 5.653 million a year earlier. Soft wheat flour exports jumped to 5.766 million tonnes from 3.744 million.</p>
<p>Barley exports reached 6.069 million tonnes against 1.559 million tonnes.</p>
<p>On Thursday the European Union granted the export of 89,200 tonnes of barley, 8,500 tonnes of oats, and 46,379 tonnes of rye.</p>
<p>The EU has closed the weekly tender for wheat exports and imposed a tax of 15 Ecus per tonne on daily soft wheat exports and of 20 ecus per tonne on soft wheat flour exports.</p>
<p>The move is aimed at keeping domestic prices and supplies under control in the face of volatile prices.</p>
</text>
<copyright>(c) Reuters Limited 1997</copyright>
<metadata>
<codes class="bip:countries:1.0">
  <code code="EEC">
    <editdetail attribution="Reuters BIP Coding Group" action="confirmed" date="1997-05-16"/>
  </code>
</codes>
<codes class="bip:industries:1.0">
  <code code="I01001">
    <editdetail attribution="Reuters BIP Coding Group" action="confirmed" date="1997-05-16"/>
  </code>
  <code code="I0100132">
    <editdetail attribution="Reuters BIP Coding Group" action="confirmed" date="1997-05-16"/>
  </code>
</codes>
<codes class="bip:topics:1.0">
  <code code="C31">
    <editdetail attribution="Reuters BIP Coding Group" action="confirmed" date="1997-05-16"/>
  </code>
  <code code="C312">
    <editdetail attribution="Reuters BIP Coding Group" action="confirmed" date="1997-05-16"/>
  </code>
  <code code="CCAT">
    <editdetail attribution="Reuters BIP Coding Group" action="confirmed" date="1997-05-16"/>
  </code>
  <code code="M14">
    <editdetail attribution="Reuters BIP Coding Group" action="confirmed" date="1997-05-16"/>
  </code>
  <code code="M141">
    <editdetail attribution="Reuters BIP Coding Group" action="confirmed" date="1997-05-16"/>
  </code>
  <code code="MCAT">
    <editdetail attribution="Reuters BIP Coding Group" action="confirmed" date="1997-05-16"/>
  </code>
</codes>
<dc element="dc.date.created" value="1997-05-16"/>
<dc element="dc.publisher" value="Reuters Holdings Plc"/>
<dc element="dc.date.published" value="1997-05-16"/>
<dc element="dc.source" value="Reuters"/>
<dc element="dc.creator.location" value="PARIS"/>
<dc element="dc.creator.location.country.name" value="FRANCE"/>
<dc element="dc.source" value="Reuters"/>
</metadata>
</newsitem>
